confluence_sync/.DS_Store
confluence_sync/__init__.py
confluence_sync/__main__.py
confluence_sync/cli.py
confluence_sync/confluence.py
confluence_sync/context.py
confluence_sync/events.py
confluence_sync/fmt.py
confluence_sync/logger.py
confluence_sync/observer.py
confluence_sync/parser/__init__.py
confluence_sync/parser/entities/xhtml-lat1.ent
confluence_sync/parser/entities/xhtml-special.ent
confluence_sync/parser/entities/xhtml-symbol.ent
confluence_sync/parser/storage.py
confluence_sync/sync.py
confluence_sync/tree.py
confluence_syncer-1.0.1.dist-info/LICENSE
confluence_syncer-1.0.1.dist-info/METADATA
confluence_syncer-1.0.1.dist-info/WHEEL
confluence_syncer-1.0.1.dist-info/entry_points.txt
confluence_syncer-1.0.1.dist-info/RECORD
