Metadata-Version: 2.3
Name: confluence-syncer
Version: 1.0.1
Summary: A utility for synchronizing page hierarchies across Confluence Data Center instances.
License: MIT
Keywords: confluence
Author: Arkhipov Nikita
Author-email: arkhipov.nr@gmail.com
Requires-Python: >=3.11
Classifier: Development Status :: 4 - Beta
Classifier: License :: OSI Approved :: MIT License
Classifier: Operating System :: OS Independent
Classifier: Programming Language :: Python :: 3
Classifier: Programming Language :: Python :: 3.11
Classifier: Topic :: Utilities
Requires-Dist: atlassian-python-api (>=3.41.8,<4.0.0)
Requires-Dist: colorlog (>=6.8.0,<7.0.0)
Requires-Dist: lxml (>=5.1.0,<6.0.0)
Requires-Dist: tqdm (>=4.66.1,<5.0.0)
Project-URL: Repository, https://github.com/ArkhipovNikita/confluence-sync
